tpgroutes/__init__.py
tpgroutes/__main__.py
tpgroutes/database.py
tpgroutes-1.0.5.dist-info/LICENSE
tpgroutes-1.0.5.dist-info/METADATA
tpgroutes-1.0.5.dist-info/WHEEL
tpgroutes-1.0.5.dist-info/entry_points.txt
tpgroutes-1.0.5.dist-info/top_level.txt
tpgroutes-1.0.5.dist-info/RECORD
