Metadata-Version: 2.1
Name: tpgroutes
Version: 1.0.5
Summary: Routes algorithm for Geneva Public Transportations, in Python
Home-page: https://github.com/tpgoffline/TpgRoutes
Author: Rémy Da Costa Faro
Author-email: remy@tpgoffline.com
License: MIT
Platform: UNKNOWN
Classifier: License :: OSI Approved :: MIT License
Classifier: Programming Language :: Python :: 3
Classifier: Programming Language :: Python :: 3.7
Requires-Dist: sqlalchemy
